[
  {
    "town": "Alangad",
    "mosque": "Alangad Juma Masjid",
    "lat": 10.125258,
    "lng": 76.30035300000002
  },
  {
    "town": "Alangad",
    "mosque": "Sunni Juma Masjid Neericode",
    "lat": 10.1196058,
    "lng": 76.2834812
  },
  {
    "town": "Alangad",
    "mosque": "Panayikulam Salafi Masjid",
    "lat": 10.1032605,
    "lng": 76.289329
  },
  {
    "town": "Alangad",
    "mosque": "Masjid Zainabi, Alangad, Kottappuram,Cheruthuruth",
    "lat": 10.1318967,
    "lng": 76.29879180000002
  },
  {
    "town": "Alangad",
    "mosque": "Muhiyudheen Juma Masjid",
    "lat": 10.1039777,
    "lng": 76.28662469999999
  },
  {
    "town": "Alangad",
    "mosque": "Salafi Masjid Neericode",
    "lat": 10.1208448,
    "lng": 76.28252830000001
  },
  {
    "town": "Alangad",
    "mosque": "MASJIDUL FALAH",
    "lat": 10.1044756,
    "lng": 76.2984661
  },
  {
    "town": "Alangad",
    "mosque": "Mazjid Thaqwa, Alangad",
    "lat": 10.8434472,
    "lng": 76.4450107
  },
  {
    "town": "Alangad",
    "mosque": "Panayikulam Juma Masjid",
    "lat": 10.1002843,
    "lng": 76.30538659999999
  },
  {
    "town": "Alangad",
    "mosque": "Najathul Islam Masjid",
    "lat": 10.0937144,
    "lng": 76.2917298
  },
  {
    "town": "Alangad",
    "mosque": "Karingamthuruth Jn. Masjid",
    "lat": 10.1088619,
    "lng": 76.2785935
  },
  {
    "town": "Alangad",
    "mosque": "Karipuzha Masjid",
    "lat": 10.1043679,
    "lng": 76.30994690000001
  },
  {
    "town": "Alangad",
    "mosque": "Edayar Juma Masjid",
    "lat": 10.0878518,
    "lng": 76.3033342
  },
  {
    "town": "Alangad",
    "mosque": "Arafa Masjid",
    "lat": 10.129324,
    "lng": 76.30007130000001
  },
  {
    "town": "Alangad",
    "mosque": "Panayikulam Central Masjid",
    "lat": 10.1023254,
    "lng": 76.30170249999999
  },
  {
    "town": "Alangad",
    "mosque": "Ansarul Islam trust, masjid",
    "lat": 10.130545,
    "lng": 76.283824
  },
  {
    "town": "Alangad",
    "mosque": "Al-Hidaya Masjid",
    "lat": 10.141443,
    "lng": 76.3151146
  },
  {
    "town": "Alangad",
    "mosque": "Musjidh Al Khidhir Juma Masjid",
    "lat": 10.0966008,
    "lng": 76.31744830000001
  },
  {
    "town": "Alangad",
    "mosque": "Karingamthuruth Juma Masjid",
    "lat": 10.1176535,
    "lng": 76.27074189999999
  },
  {
    "town": "Alangad",
    "mosque": "Neericode",
    "lat": 10.1123,
    "lng": 76.2830973
  }
]