[
  {
    "town": "Alappad",
    "mosque": "Juma Masjid - Puthutheruve",
    "lat": 9.1183397,
    "lng": 76.4976765
  },
  {
    "town": "Alappad",
    "mosque": "Clappana Juma Masjid",
    "lat": 9.108632,
    "lng": 76.4961904
  },
  {
    "town": "Alappad",
    "mosque": "Ikkara Masjid",
    "lat": 9.0469025,
    "lng": 76.5182212
  },
  {
    "town": "Alappad",
    "mosque": "Alummoottil Masjid And Madrasa",
    "lat": 9.0697532,
    "lng": 76.5134403
  },
  {
    "town": "Alappad",
    "mosque": "Juma Musjid",
    "lat": 9.116449200000002,
    "lng": 76.4790019
  },
  {
    "town": "Alappad",
    "mosque": "ഇസ്സത്തുൽ ഇസ്‌ലാം മസ്ജിദ്",
    "lat": 9.0578536,
    "lng": 76.5052097
  },
  {
    "town": "Alappad",
    "mosque": "Masjid ul Qadiriya",
    "lat": 9.0020727,
    "lng": 76.536622
  },
  {
    "town": "Alappad",
    "mosque": "Panachamoodu Muslim Nuzrath Jummah Masjid",
    "lat": 9.0790565,
    "lng": 76.5158656
  },
  {
    "town": "Alappad",
    "mosque": "Kottara Masjid",
    "lat": 9.0359278,
    "lng": 76.5205522
  },
  {
    "town": "Alappad",
    "mosque": "Thatbiyyathul Islam masjid",
    "lat": 9.1129622,
    "lng": 76.4914484
  },
  {
    "town": "Alappad",
    "mosque": "Maruthoorkulangara Juma Masjid",
    "lat": 9.0525979,
    "lng": 76.5111744
  },
  {
    "town": "Alappad",
    "mosque": "kozhikod Market masjid🕌",
    "lat": 9.0332451,
    "lng": 76.5176694
  },
  {
    "town": "Alappad",
    "mosque": "Panoorayth Masjid",
    "lat": 9.0455876,
    "lng": 76.5223364
  },
  {
    "town": "Alappad",
    "mosque": "Masjidul Eeman",
    "lat": 9.1116797,
    "lng": 76.49595099999999
  },
  {
    "town": "Alappad",
    "mosque": "Sahaba Masjid",
    "lat": 9.0100224,
    "lng": 76.5400609
  },
  {
    "town": "Alappad",
    "mosque": "Kuttivattom Juma Masjid",
    "lat": 9.0308456,
    "lng": 76.5429316
  },
  {
    "town": "Alappad",
    "mosque": "Qubbathul Mahabbha Masjid",
    "lat": 9.126030199999999,
    "lng": 76.5033095
  },
  {
    "town": "Alappad",
    "mosque": "Varavila Muslim Jamath Masjid(Juma Masjid)",
    "lat": 9.118964499999999,
    "lng": 76.5055576
  },
  {
    "town": "Alappad",
    "mosque": "Padinjaretheruvu Juma Masjid",
    "lat": 9.1355638,
    "lng": 76.507257
  },
  {
    "town": "Alappad",
    "mosque": "Sheikh Masjid",
    "lat": 9.074275499999999,
    "lng": 76.5330439
  }
]