[
  {
    "town": "Azhikode",
    "mosque": "Azhikode Jama-athul Islam Juma Masjid, Vankulathvayal",
    "lat": 11.9206046,
    "lng": 75.3359014
  },
  {
    "town": "Azhikode",
    "mosque": "Azhicode Juma Masjid",
    "lat": 8.5729162,
    "lng": 76.99814359999999
  },
  {
    "town": "Azhikode",
    "mosque": "Puthanpally Juma Masjid",
    "lat": 10.1954527,
    "lng": 76.17023309999999
  },
  {
    "town": "Azhikode",
    "mosque": "Muhyadheen Masjid",
    "lat": 10.2031618,
    "lng": 76.155793
  },
  {
    "town": "Azhikode",
    "mosque": "Darul Aman Masjid",
    "lat": 10.1948858,
    "lng": 76.1730374
  },
  {
    "town": "Azhikode",
    "mosque": "Salafi Masjid",
    "lat": 10.2055816,
    "lng": 76.16538419999999
  },
  {
    "town": "Azhikode",
    "mosque": "Salafi Masjid",
    "lat": 11.9083138,
    "lng": 75.3428314
  },
  {
    "town": "Azhikode",
    "mosque": "MASJIDURRAHMA MOSQUE",
    "lat": 10.1834253,
    "lng": 76.16292039999999
  },
  {
    "town": "Azhikode",
    "mosque": "Masjid Al Huda",
    "lat": 10.2086075,
    "lng": 76.158526
  },
  {
    "town": "Azhikode",
    "mosque": "Mohiyuddin Juma Masjid and Jamaliya Madrasa",
    "lat": 11.8956945,
    "lng": 75.3499819
  },
  {
    "town": "Azhikode",
    "mosque": "Kappakadav Jama'ath Masjid",
    "lat": 11.9414376,
    "lng": 75.3170574
  },
  {
    "town": "Azhikode",
    "mosque": "Poothappara Juma Masjid",
    "lat": 11.9109007,
    "lng": 75.341827
  },
  {
    "town": "Azhikode",
    "mosque": "Hamadaniya Juma Mazjid",
    "lat": 10.1900812,
    "lng": 76.167385
  },
  {
    "town": "Azhikode",
    "mosque": "Masjid Sahaba Kappalbazar",
    "lat": 10.1972357,
    "lng": 76.1660785
  },
  {
    "town": "Azhikode",
    "mosque": "Salafi Masjid Azheekkal",
    "lat": 11.9438824,
    "lng": 75.3047445
  },
  {
    "town": "Azhikode",
    "mosque": "Chakkarapara Badar Juma Masjid",
    "lat": 11.9037191,
    "lng": 75.34201759999999
  },
  {
    "town": "Azhikode",
    "mosque": "Badarul Huda Masjid",
    "lat": 11.9234185,
    "lng": 75.3158064
  },
  {
    "town": "Azhikode",
    "mosque": "AZHIKODE VALIYAPALLI JUMA MASJID",
    "lat": 8.572776,
    "lng": 76.9985081
  },
  {
    "town": "Azhikode",
    "mosque": "MASJID UL HUDA, JUMA MASJID",
    "lat": 10.206146,
    "lng": 76.17213319999999
  },
  {
    "town": "Azhikode",
    "mosque": "Thwaha mahlara",
    "lat": 10.1916388,
    "lng": 76.1697212
  }
]