[
  {
    "town": "Karuvarakundu",
    "mosque": "Panathummal Juma Masjid",
    "lat": 11.1092122,
    "lng": 76.3394514
  },
  {
    "town": "Karuvarakundu",
    "mosque": "KARUVARAKUNDU ANGADI JUMA MASJID",
    "lat": 11.1190991,
    "lng": 76.3347143
  },
  {
    "town": "Karuvarakundu",
    "mosque": "Juma Masjid",
    "lat": 11.1236029,
    "lng": 76.3344202
  },
  {
    "town": "Karuvarakundu",
    "mosque": "Khankhah Nooriyya Karuvarakkundu",
    "lat": 11.1204541,
    "lng": 76.33654779999999
  },
  {
    "town": "Karuvarakundu",
    "mosque": "Darunnajath Masjid",
    "lat": 11.1151307,
    "lng": 76.3258688
  },
  {
    "town": "Karuvarakundu",
    "mosque": "Kizhakkethala Juma Masjid",
    "lat": 11.1244917,
    "lng": 76.3408018
  },
  {
    "town": "Karuvarakundu",
    "mosque": "Mukkatta Masjid",
    "lat": 11.1255895,
    "lng": 76.3499262
  },
  {
    "town": "Karuvarakundu",
    "mosque": "Masjid",
    "lat": 11.1220268,
    "lng": 76.33681709999999
  },
  {
    "town": "Karuvarakundu",
    "mosque": "Juma Masjid - Kannath",
    "lat": 11.1304773,
    "lng": 76.3435038
  },
  {
    "town": "Karuvarakundu",
    "mosque": "Masjidussalam",
    "lat": 11.1212775,
    "lng": 76.3365685
  },
  {
    "town": "Karuvarakundu",
    "mosque": "SALAFI MASJID KARUVARAKUND",
    "lat": 11.1239456,
    "lng": 76.3419995
  },
  {
    "town": "Karuvarakundu",
    "mosque": "Salafi Masjid Maruthingal",
    "lat": 11.1248748,
    "lng": 76.33884359999999
  },
  {
    "town": "Karuvarakundu",
    "mosque": "Punnakad Masjid",
    "lat": 11.1134447,
    "lng": 76.3258029
  },
  {
    "town": "Karuvarakundu",
    "mosque": "Kerala Juma Masjid Karuvarakund",
    "lat": 11.1423532,
    "lng": 76.3479835
  },
  {
    "town": "Karuvarakundu",
    "mosque": "Masjid",
    "lat": 11.1120098,
    "lng": 76.3410638
  },
  {
    "town": "Karuvarakundu",
    "mosque": "Pulvetta Madeena Masjid",
    "lat": 11.1127413,
    "lng": 76.34058329999999
  },
  {
    "town": "Karuvarakundu",
    "mosque": "Town Masjid",
    "lat": 11.1214849,
    "lng": 76.3489465
  },
  {
    "town": "Karuvarakundu",
    "mosque": "Chirakkal Kundu Masjid",
    "lat": 11.1155275,
    "lng": 76.33995449999999
  },
  {
    "town": "Karuvarakundu",
    "mosque": "UK Colony Masjid",
    "lat": 11.1298078,
    "lng": 76.3549721
  },
  {
    "town": "Karuvarakundu",
    "mosque": "Masjidul Huda",
    "lat": 11.1244918,
    "lng": 76.3408017
  }
]