[
  {
    "town": "Kottappadam",
    "mosque": "Juma Masjid Kottoppadam",
    "lat": 10.9960145,
    "lng": 76.3960271
  },
  {
    "town": "Kottappadam",
    "mosque": "Masjid",
    "lat": 11.0045487,
    "lng": 76.385914
  },
  {
    "town": "Kottappadam",
    "mosque": "Ambazhakode Juma Masjid",
    "lat": 11.0054196,
    "lng": 76.415925
  },
  {
    "town": "Kottappadam",
    "mosque": "Theyyottuchira Juma Masjid",
    "lat": 10.9904238,
    "lng": 76.36784639999999
  },
  {
    "town": "Kottappadam",
    "mosque": "East Kombam Masjid",
    "lat": 10.9775865,
    "lng": 76.3936427
  },
  {
    "town": "Kottappadam",
    "mosque": "Salafi Juma Masjid Kottopadam",
    "lat": 10.9966695,
    "lng": 76.39253479999999
  },
  {
    "town": "Kottappadam",
    "mosque": "Kodakkadu Vappa (Ka. Ma) Makam Shareef",
    "lat": 10.981638,
    "lng": 76.38344599999999
  },
  {
    "town": "Kottappadam",
    "mosque": "Aryambavu Town Juma Masjid",
    "lat": 10.9793483,
    "lng": 76.4049903
  },
  {
    "town": "Kottappadam",
    "mosque": "Sunni Masjid,Kundlakkad",
    "lat": 11.0039684,
    "lng": 76.4078414
  },
  {
    "town": "Kottappadam",
    "mosque": "Masjid salama",
    "lat": 11.0062289,
    "lng": 76.39412550000002
  },
  {
    "town": "Kottappadam",
    "mosque": "Salafi Masjid",
    "lat": 10.9799678,
    "lng": 76.38074189999999
  },
  {
    "town": "Kottappadam",
    "mosque": "Masjid Rahman",
    "lat": 10.9945498,
    "lng": 76.3998696
  },
  {
    "town": "Kottappadam",
    "mosque": "Masjid Thaqwa Anakkallu",
    "lat": 11.0070924,
    "lng": 76.3907911
  },
  {
    "town": "Kottappadam",
    "mosque": "Juma Masjid Vadaserripuram",
    "lat": 10.9838943,
    "lng": 76.3922788
  },
  {
    "town": "Kottappadam",
    "mosque": "Chaattakkundu Masjid",
    "lat": 11.0151321,
    "lng": 76.3813076
  },
  {
    "town": "Kottappadam",
    "mosque": "Koduvalippuram Juma Masjid",
    "lat": 11.002214,
    "lng": 76.40205519999999
  },
  {
    "town": "Kottappadam",
    "mosque": "Kodakkad Juma Masjid",
    "lat": 10.9803867,
    "lng": 76.37887649999999
  },
  {
    "town": "Kottappadam",
    "mosque": "Masjid Al Salama",
    "lat": 11.0113774,
    "lng": 76.4088166
  },
  {
    "town": "Kottappadam",
    "mosque": "Kuthirampatta Maqam",
    "lat": 10.9970355,
    "lng": 76.3914746
  },
  {
    "town": "Kottappadam",
    "mosque": "Puttanikkad Juma Masjid",
    "lat": 11.013608,
    "lng": 76.40424999999999
  }
]