[
  {
    "town": "Moorkanade",
    "mosque": "Elippakulam Muslim Jamath",
    "lat": 9.1512704,
    "lng": 76.55314109999999
  },
  {
    "town": "Moorkanade",
    "mosque": "Kuttitheruvu Muslim Jamaath (കുറ്റിത്തെരുവ് മുസ്ലിം ജമാഅത് )",
    "lat": 9.1790871,
    "lng": 76.522847
  },
  {
    "town": "Moorkanade",
    "mosque": "Kappil Mekku Juma Masjid",
    "lat": 9.153502,
    "lng": 76.5271087
  },
  {
    "town": "Moorkanade",
    "mosque": "Kappil East Mosque",
    "lat": 9.1419154,
    "lng": 76.5398781
  },
  {
    "town": "Moorkanade",
    "mosque": "Moorkanad Juma Masjid",
    "lat": 10.9538249,
    "lng": 76.0350593
  },
  {
    "town": "Moorkanade",
    "mosque": "Keerikkadu Masjid",
    "lat": 9.1828725,
    "lng": 76.484678
  },
  {
    "town": "Moorkanade",
    "mosque": "Kattachira jumah Masjid",
    "lat": 9.152263399999999,
    "lng": 76.5391097
  },
  {
    "town": "Moorkanade",
    "mosque": "Masjid Noor",
    "lat": 9.193166999999999,
    "lng": 76.49019
  },
  {
    "town": "Moorkanade",
    "mosque": "MASJID",
    "lat": 10.894926,
    "lng": 76.1498605
  },
  {
    "town": "Moorkanade",
    "mosque": "Oachira North Masjid",
    "lat": 9.140597,
    "lng": 76.5118897
  },
  {
    "town": "Moorkanade",
    "mosque": "ONNAMKUTTY MASJID (Roohiya masjid & madrasa)",
    "lat": 9.173472199999999,
    "lng": 76.51850379999999
  },
  {
    "town": "Moorkanade",
    "mosque": "Al khadiriyya masjid",
    "lat": 9.1483195,
    "lng": 76.54630680000001
  },
  {
    "town": "Moorkanade",
    "mosque": "Padinjaretheruvu Juma Masjid",
    "lat": 9.1355638,
    "lng": 76.507257
  },
  {
    "town": "Moorkanade",
    "mosque": "kannanakuzhy mosque",
    "lat": 9.156098799999999,
    "lng": 76.56239339999999
  },
  {
    "town": "Moorkanade",
    "mosque": "HHYS Madrasa",
    "lat": 9.1771437,
    "lng": 76.5298007
  },
  {
    "town": "Moorkanade",
    "mosque": "Chunakkara North Nooril Islam Masjid",
    "lat": 9.185590399999999,
    "lng": 76.6003078
  },
  {
    "town": "Moorkanade",
    "mosque": "Badarul Huda Juma Masjid",
    "lat": 9.188279399999999,
    "lng": 76.49327029999999
  },
  {
    "town": "Moorkanade",
    "mosque": "Oachira Town Masjid. ടൗൺ ജുമാ മസ്ജിദ്",
    "lat": 9.134666800000002,
    "lng": 76.5127289
  },
  {
    "town": "Moorkanade",
    "mosque": "Kadathoor Masjid (Vavvakavu Muslim Jama-ath Qabarsthan)",
    "lat": 9.0996233,
    "lng": 76.5271626
  },
  {
    "town": "Moorkanade",
    "mosque": "Moorkanad Salafi Juma Masjid",
    "lat": 11.241054,
    "lng": 76.0532186
  }
]