[
  {
    "town": "Nelliyampathy",
    "mosque": "Muhiyuddeen Juma Masjid",
    "lat": 10.5323454,
    "lng": 76.69269349999999
  },
  {
    "town": "Nelliyampathy",
    "mosque": "Aluvassery Mosque അളുവശ്ശേരി മോസ്ക്",
    "lat": 10.5841124,
    "lng": 76.6020611
  },
  {
    "town": "Nelliyampathy",
    "mosque": "Koonampalam Juma Masjid",
    "lat": 10.5160324,
    "lng": 76.6705635
  },
  {
    "town": "Nelliyampathy",
    "mosque": "Pothupara Juma Masjid",
    "lat": 10.5076094,
    "lng": 76.6777127
  }
]