[
  {
    "town": "Onchiyam",
    "mosque": "Onchiyam Juma Masjid",
    "lat": 11.6543185,
    "lng": 75.5737864
  },
  {
    "town": "Onchiyam",
    "mosque": "Kunnummal badriya masjid",
    "lat": 11.6552123,
    "lng": 75.5691804
  },
  {
    "town": "Onchiyam",
    "mosque": "Veeroli Musjid",
    "lat": 11.6680875,
    "lng": 75.57520559999999
  },
  {
    "town": "Onchiyam",
    "mosque": "Muhyudheen Juma Masjid Nellacheri",
    "lat": 11.6686971,
    "lng": 75.582929
  },
  {
    "town": "Onchiyam",
    "mosque": "Navathu musjid",
    "lat": 11.6548883,
    "lng": 75.579059
  },
  {
    "town": "Onchiyam",
    "mosque": "Noorul Eman masjid",
    "lat": 11.6574981,
    "lng": 75.5839862
  },
  {
    "town": "Onchiyam",
    "mosque": "Kunhipally Juma Masjid",
    "lat": 11.6775878,
    "lng": 75.5510151
  },
  {
    "town": "Onchiyam",
    "mosque": "Madeenathunnoor",
    "lat": 11.6737071,
    "lng": 75.5802971
  },
  {
    "town": "Onchiyam",
    "mosque": "Kallerimukku Kottoth Cutting Road Onjiyam",
    "lat": 11.6542332,
    "lng": 75.5725932
  },
  {
    "town": "Onchiyam",
    "mosque": "Valiya parambath Masjid",
    "lat": 11.6601041,
    "lng": 75.5758893
  },
  {
    "town": "Onchiyam",
    "mosque": "Thottungal masjid",
    "lat": 11.6637162,
    "lng": 75.589297
  },
  {
    "town": "Onchiyam",
    "mosque": "Juma masjid Kannookkara",
    "lat": 11.6534754,
    "lng": 75.5619095
  },
  {
    "town": "Onchiyam",
    "mosque": "Thattolikkara masjid",
    "lat": 11.6637891,
    "lng": 75.56729299999999
  },
  {
    "town": "Onchiyam",
    "mosque": "Eramala Juma Masjid",
    "lat": 11.6809701,
    "lng": 75.5930802
  },
  {
    "town": "Onchiyam",
    "mosque": "Maadaakkara Muhyudheen Juma Masjid",
    "lat": 11.6530087,
    "lng": 75.5565206
  },
  {
    "town": "Onchiyam",
    "mosque": "Mukkali Muslim Palli",
    "lat": 11.6677383,
    "lng": 75.5593918
  },
  {
    "town": "Onchiyam",
    "mosque": "Salafi Juma Masjid",
    "lat": 11.6554729,
    "lng": 75.5609002
  },
  {
    "town": "Onchiyam",
    "mosque": "Monthal Juma Masjid",
    "lat": 11.6939587,
    "lng": 75.5644317
  },
  {
    "town": "Onchiyam",
    "mosque": "Masjid Aboobacker Siddeeque",
    "lat": 11.6304406,
    "lng": 75.5906933
  },
  {
    "town": "Onchiyam",
    "mosque": "BHEECHUMMA MASJID",
    "lat": 11.6576269,
    "lng": 75.55438869999999
  }
]