[
  {
    "town": "Parappoor",
    "mosque": "Mullapparamb Masjid",
    "lat": 11.0072041,
    "lng": 75.9901053
  },
  {
    "town": "Parappoor",
    "mosque": "Veenalukkal Sideeque Juma Masjid",
    "lat": 11.0130395,
    "lng": 75.99362649999999
  },
  {
    "town": "Parappoor",
    "mosque": "Masjid",
    "lat": 11.0130277,
    "lng": 75.99685769999999
  },
  {
    "town": "Parappoor",
    "mosque": "parappur Masjid noor",
    "lat": 11.016051,
    "lng": 75.9950825
  },
  {
    "town": "Parappoor",
    "mosque": "Sunni Masjid",
    "lat": 11.0098281,
    "lng": 75.9971898
  },
  {
    "town": "Parappoor",
    "mosque": "Kottupara Juma Masjid",
    "lat": 11.0205365,
    "lng": 75.9896685
  },
  {
    "town": "Parappoor",
    "mosque": "Muslim masjid",
    "lat": 11.015513,
    "lng": 75.9902359
  },
  {
    "town": "Parappoor",
    "mosque": "Salafi Juma Masjid",
    "lat": 11.0176584,
    "lng": 75.9955295
  },
  {
    "town": "Parappoor",
    "mosque": "Parappur Puzhachal Masjid",
    "lat": 11.0307173,
    "lng": 75.9853315
  },
  {
    "town": "Parappoor",
    "mosque": "Kalliyathupara Juma Masjid",
    "lat": 11.02001,
    "lng": 75.9856298
  },
  {
    "town": "Parappoor",
    "mosque": "Masjid parayil",
    "lat": 11.024517,
    "lng": 75.9858684
  },
  {
    "town": "Parappoor",
    "mosque": "PARAPPUR Vadakkumuri Juma Masjid",
    "lat": 11.0293601,
    "lng": 75.9846601
  },
  {
    "town": "Parappoor",
    "mosque": "Masjidul Farooq",
    "lat": 11.0087048,
    "lng": 75.9934045
  },
  {
    "town": "Parappoor",
    "mosque": "Masjidunnoor, Neerilla Parappur.",
    "lat": 10.9616055,
    "lng": 76.0601436
  },
  {
    "town": "Parappoor",
    "mosque": "Thekkekulambu masjid",
    "lat": 11.0099068,
    "lng": 75.9880403
  },
  {
    "town": "Parappoor",
    "mosque": "Masjidul Hamidi Parapur",
    "lat": 10.5618344,
    "lng": 76.120446
  },
  {
    "town": "Parappoor",
    "mosque": "മസ്ജിദ് സ്വഹാബാ",
    "lat": 11.0188825,
    "lng": 75.9982015
  },
  {
    "town": "Parappoor",
    "mosque": "Millumpadi Bilal Masjid",
    "lat": 11.0200145,
    "lng": 75.9828418
  },
  {
    "town": "Parappoor",
    "mosque": "Masjid Rahman Sunni Mahallu Parappur",
    "lat": 10.9602133,
    "lng": 76.0559779
  },
  {
    "town": "Parappoor",
    "mosque": "Farook Campus Masjid",
    "lat": 11.0063712,
    "lng": 75.9939861
  }
]