[
  {
    "town": "Thrippunithura",
    "mosque": "Thripunithura Town Juma Masjid",
    "lat": 9.9453383,
    "lng": 76.35168089999999
  },
  {
    "town": "Thrippunithura",
    "mosque": "Masjid Road 1",
    "lat": 9.945473,
    "lng": 76.3516743
  },
  {
    "town": "Thrippunithura",
    "mosque": "Thajul Islam Juma Masjid Petta",
    "lat": 9.9503989,
    "lng": 76.3330735
  },
  {
    "town": "Thrippunithura",
    "mosque": "Masjid",
    "lat": 9.9503895,
    "lng": 76.3330478
  },
  {
    "town": "Thrippunithura",
    "mosque": "Salafi Juma Masjid സലഫി ജുമാ മസ്ജിദ്",
    "lat": 9.9644151,
    "lng": 76.3188162
  },
  {
    "town": "Thrippunithura",
    "mosque": "Juma Masjid Maradu",
    "lat": 9.9289133,
    "lng": 76.3304421
  },
  {
    "town": "Thrippunithura",
    "mosque": "Juma Masjid",
    "lat": 9.9874298,
    "lng": 76.3296919
  },
  {
    "town": "Thrippunithura",
    "mosque": "Vyttila Jumua Masjid",
    "lat": 9.9696091,
    "lng": 76.31849969999999
  },
  {
    "town": "Thrippunithura",
    "mosque": "Masjidul Himaya Jumah Masjid",
    "lat": 9.9232827,
    "lng": 76.3171771
  },
  {
    "town": "Thrippunithura",
    "mosque": "Thevara Juma Masjid",
    "lat": 9.9450304,
    "lng": 76.2939258
  },
  {
    "town": "Thrippunithura",
    "mosque": "Punnurunni Juma Masjid",
    "lat": 9.9913241,
    "lng": 76.3089475
  },
  {
    "town": "Thrippunithura",
    "mosque": "Badaria Juma Masjid",
    "lat": 9.9666902,
    "lng": 76.29066999999999
  },
  {
    "town": "Thrippunithura",
    "mosque": "Noor Juma Masjid, Market Road Ernakulam",
    "lat": 9.9748778,
    "lng": 76.2811139
  },
  {
    "town": "Thrippunithura",
    "mosque": "Muhiyudheen Juma Masjid chittethukara",
    "lat": 9.9998141,
    "lng": 76.3528374
  },
  {
    "town": "Thrippunithura",
    "mosque": "Pallippadi Juma Masjid And Noorul Islam Madrasa",
    "lat": 9.990691799999999,
    "lng": 76.318557
  },
  {
    "town": "Thrippunithura",
    "mosque": "Salafi Juma Masjid",
    "lat": 9.9660652,
    "lng": 76.299605
  },
  {
    "town": "Thrippunithura",
    "mosque": "Salafi Juma Masjid Pallimukku",
    "lat": 9.962762399999999,
    "lng": 76.28779879999999
  },
  {
    "town": "Thrippunithura",
    "mosque": "Vennala Muslim Jama-ath Vadakkaneth Masjid",
    "lat": 9.9927901,
    "lng": 76.3272124
  },
  {
    "town": "Thrippunithura",
    "mosque": "Kathrikadav Salafi Masjid",
    "lat": 9.9832356,
    "lng": 76.29755770000001
  },
  {
    "town": "Thrippunithura",
    "mosque": "Central Juma Masjid",
    "lat": 9.9806334,
    "lng": 76.27778769999999
  }
]