[
  {
    "town": "Veeyapuramh",
    "mosque": "Vavvakkavu Juma Masjid",
    "lat": 9.101008799999999,
    "lng": 76.5232461
  },
  {
    "town": "Veeyapuramh",
    "mosque": "Kappil Mekku Juma Masjid",
    "lat": 9.153502,
    "lng": 76.5271087
  },
  {
    "town": "Veeyapuramh",
    "mosque": "Elippakulam Muslim Jamath",
    "lat": 9.1512704,
    "lng": 76.55314109999999
  },
  {
    "town": "Veeyapuramh",
    "mosque": "Kuttitheruvu Muslim Jamaath (കുറ്റിത്തെരുവ് മുസ്ലിം ജമാഅത് )",
    "lat": 9.1790871,
    "lng": 76.522847
  },
  {
    "town": "Veeyapuramh",
    "mosque": "Kappil East Mosque",
    "lat": 9.1419154,
    "lng": 76.5398781
  },
  {
    "town": "Veeyapuramh",
    "mosque": "Kizhakke jumaah Palli , Vettiyar",
    "lat": 9.228542299999999,
    "lng": 76.59267249999999
  },
  {
    "town": "Veeyapuramh",
    "mosque": "Juma Masjid",
    "lat": 9.3329913,
    "lng": 76.4665861
  },
  {
    "town": "Veeyapuramh",
    "mosque": "Kattachira jumah Masjid",
    "lat": 9.152263399999999,
    "lng": 76.5391097
  },
  {
    "town": "Veeyapuramh",
    "mosque": "Kurungappally Masjid(Vavvakkavu Muslim Jama-ath)",
    "lat": 9.111292299999999,
    "lng": 76.5338252
  },
  {
    "town": "Veeyapuramh",
    "mosque": "Sheikh Masjid",
    "lat": 9.074275499999999,
    "lng": 76.5330439
  },
  {
    "town": "Veeyapuramh",
    "mosque": "Kadathoor Masjid (Vavvakavu Muslim Jama-ath Qabarsthan)",
    "lat": 9.0996233,
    "lng": 76.5271626
  },
  {
    "town": "Veeyapuramh",
    "mosque": "Sasthampoika Juma Masjid",
    "lat": 9.0968219,
    "lng": 76.533002
  },
  {
    "town": "Veeyapuramh",
    "mosque": "Cheravallay Juma Masjid",
    "lat": 9.169492,
    "lng": 76.512638
  },
  {
    "town": "Veeyapuramh",
    "mosque": "ONNAMKUTTY MASJID (Roohiya masjid & madrasa)",
    "lat": 9.173472199999999,
    "lng": 76.51850379999999
  },
  {
    "town": "Veeyapuramh",
    "mosque": "HHYS Madrasa",
    "lat": 9.1771437,
    "lng": 76.5298007
  },
  {
    "town": "Veeyapuramh",
    "mosque": "Badariyya Masjid",
    "lat": 9.1372099,
    "lng": 76.5450197
  },
  {
    "town": "Veeyapuramh",
    "mosque": "Juma Masjid - Puthutheruve",
    "lat": 9.1183397,
    "lng": 76.4976765
  },
  {
    "town": "Veeyapuramh",
    "mosque": "Nooraniyya Juma Masjid ,West Kaippuram",
    "lat": 10.8774078,
    "lng": 76.1346736
  },
  {
    "town": "Veeyapuramh",
    "mosque": "Pathiyoor Juma Masjid",
    "lat": 9.210909599999999,
    "lng": 76.4977813
  },
  {
    "town": "Veeyapuramh",
    "mosque": "Valliyakulangara Juma Masjid",
    "lat": 9.120825,
    "lng": 76.5184814
  }
]